hostlist/__init__.py
hostlist/cla_hostlist.py
hostlist/hostlist.py
hostlist/unittest_hostlist.py
py_hostlist-0.0.2.dev0.dist-info/LICENSE
py_hostlist-0.0.2.dev0.dist-info/METADATA
py_hostlist-0.0.2.dev0.dist-info/NOTICE
py_hostlist-0.0.2.dev0.dist-info/WHEEL
py_hostlist-0.0.2.dev0.dist-info/entry_points.txt
py_hostlist-0.0.2.dev0.dist-info/top_level.txt
py_hostlist-0.0.2.dev0.dist-info/RECORD
