Metadata-Version: 2.1
Name: py-hostlist
Version: 0.0.2.dev0
Summary: A slurm-style hostlist processor.
Home-page: https://github.com/llnl/py-hostlist
Author: Christopher Moussa
Author-email: moussa1@llnl.gov
License: UNKNOWN
Platform: UNKNOWN
Classifier: Programming Language :: Python :: 3
Classifier: License :: OSI Approved :: MIT License
Classifier: Operating System :: OS Independent
